irctokens/__init__.py
irctokens/const.py
irctokens/formatting.py
irctokens/hostmask.py
irctokens/line.py
irctokens/py.typed
irctokens/stateful.py
test/__init__.py
test/format.py
test/hostmask.py
test/parser_tests.py
test/stateful_decode.py
test/stateful_encode.py
test/tokenise.py
irctokens-2.0.2.dist-info/LICENSE
irctokens-2.0.2.dist-info/METADATA
irctokens-2.0.2.dist-info/WHEEL
irctokens-2.0.2.dist-info/top_level.txt
irctokens-2.0.2.dist-info/RECORD
