Metadata-Version: 2.1
Name: irctokens
Version: 2.0.2
Summary: RFC1459 and IRCv3 protocol tokeniser
Home-page: https://github.com/jesopo/irctokens
Author: jesopo
Author-email: pip@jesopo.uk
License: UNKNOWN
Platform: UNKNOWN
Classifier: Programming Language :: Python :: 3
Classifier: License :: OSI Approved :: MIT License
Classifier: Operating System :: OS Independent
Classifier: Operating System :: POSIX
Classifier: Operating System :: Microsoft :: Windows
Classifier: Topic :: Communications :: Chat :: Internet Relay Chat
Requires-Python: >=3.6
